jaxformers/__init__.py
jaxformers/attention.py
jaxformers/blocks.py
jaxformers/decoder.py
jaxformers/encoder.py
jaxformers/encoding.py
jaxformers/normalization.py
jaxformers/py.typed
jaxformers/transformer.py
jaxformers/utils.py
jaxformers-0.0.1.dev1.dist-info/METADATA
jaxformers-0.0.1.dev1.dist-info/WHEEL
jaxformers-0.0.1.dev1.dist-info/licenses/LICENSE
jaxformers-0.0.1.dev1.dist-info/RECORD
